pypeh/__init__.py
pypeh/py.typed
pypeh/adapters/__init__.py
pypeh/adapters/inbound/__init__.py
pypeh/adapters/outbound/__init__.py
pypeh/adapters/outbound/dataops/__init__.py
pypeh/adapters/outbound/dataops/dataframe_adapter.py
pypeh/adapters/outbound/enrichment/__init__.py
pypeh/adapters/outbound/enrichment/dataframe_adapter.py
pypeh/adapters/outbound/export/__init__.py
pypeh/adapters/outbound/export/xlsx.py
pypeh/adapters/outbound/persistence/__init__.py
pypeh/adapters/outbound/persistence/dataframe.py
pypeh/adapters/outbound/persistence/hosts.py
pypeh/adapters/outbound/persistence/rocrate.py
pypeh/adapters/outbound/persistence/serializations.py
pypeh/adapters/outbound/persistence/sql.py
pypeh/adapters/outbound/validation/pandera_adapter/__init__.py
pypeh/adapters/outbound/validation/pandera_adapter/check_functions.py
pypeh/adapters/outbound/validation/pandera_adapter/parsers.py
pypeh/adapters/outbound/validation/pandera_adapter/validation_adapter.py
pypeh/core/__init__.py
pypeh/core/provenance.py
pypeh/core/cache/__init__.py
pypeh/core/cache/containers.py
pypeh/core/cache/utils.py
pypeh/core/interfaces/__init__.py
pypeh/core/interfaces/inbound/__init__.py
pypeh/core/interfaces/inbound/dataops.py
pypeh/core/interfaces/outbound/__init__.py
pypeh/core/interfaces/outbound/dataops.py
pypeh/core/interfaces/outbound/export.py
pypeh/core/interfaces/outbound/persistence.py
pypeh/core/models/__init__.py
pypeh/core/models/constants.py
pypeh/core/models/graph.py
pypeh/core/models/internal_data_layout.py
pypeh/core/models/proxy.py
pypeh/core/models/settings.py
pypeh/core/models/transform.py
pypeh/core/models/typing.py
pypeh/core/models/uri_regex.py
pypeh/core/models/validation_dto.py
pypeh/core/models/validation_errors.py
pypeh/core/session/__init__.py
pypeh/core/session/connections.py
pypeh/core/session/session.py
pypeh/core/utils/__init__.py
pypeh/core/utils/linkml_schema.py
pypeh/core/utils/namespaces.py
pypeh/core/utils/resolve_identifiers.py
pypeh-0.1.3.dist-info/METADATA
pypeh-0.1.3.dist-info/WHEEL
pypeh-0.1.3.dist-info/licenses/LICENSE
pypeh-0.1.3.dist-info/RECORD
